README.md
__init__.py
access.py
access_config.py
scan.py
setup.py
smart.py
syrah.py
AI/__init__.py
AI/ai.py
modules/__init__.py
modules/analytics.py
modules/db.py
modules/exploits.py
modules/json.py
modules/ranks.py
modules/sort.py
syrahsearch.egg-info/PKG-INFO
syrahsearch.egg-info/SOURCES.txt
syrahsearch.egg-info/dependency_links.txt
syrahsearch.egg-info/entry_points.txt
syrahsearch.egg-info/not-zip-safe
syrahsearch.egg-info/requires.txt
syrahsearch.egg-info/top_level.txt