Metadata-Version: 1.0
Name: syrahsearch
Version: 0.0.0.2.2
Summary: Command-line search engine with some cool machine learning solutions.
Home-page: https://github.com/syrahsearch/syrah
Author: Kamil Boberek
Author-email: notimportant@protonmail.com
License: MIT
Platform: UNKNOWN
